README.md
setup.py
lonestar/__init__.py
lonestar.egg-info/PKG-INFO
lonestar.egg-info/SOURCES.txt
lonestar.egg-info/dependency_links.txt
lonestar.egg-info/top_level.txt